sklearn_crfsuite/__init__.py
sklearn_crfsuite/_fileresource.py
sklearn_crfsuite/compat.py
sklearn_crfsuite/estimator.py
sklearn_crfsuite/metrics.py
sklearn_crfsuite/scorers.py
sklearn_crfsuite/trainer.py
sklearn_crfsuite/utils.py
sklearn_crfsuite-0.5.0.dist-info/METADATA
sklearn_crfsuite-0.5.0.dist-info/WHEEL
sklearn_crfsuite-0.5.0.dist-info/top_level.txt
sklearn_crfsuite-0.5.0.dist-info/RECORD
