Metadata-Version: 2.1
Name: sklearn-crfsuite
Version: 0.5.0
Summary: CRFsuite (python-crfsuite) wrapper which provides interface simlar to scikit-learn
Home-page: https://github.com/TeamHG-Memex/sklearn-crfsuite
Author: Mikhail Korobov
Author-email: kmike84@gmail.com
License: MIT license
Classifier: Development Status :: 3 - Alpha
Classifier: License :: OSI Approved :: MIT License
Classifier: Intended Audience :: Developers
Classifier: Operating System :: OS Independent
Classifier: Programming Language :: Python
Classifier: Programming Language :: Python :: 3
Classifier: Programming Language :: Python :: 3.8
Classifier: Programming Language :: Python :: 3.9
Classifier: Programming Language :: Python :: 3.10
Classifier: Programming Language :: Python :: 3.11
Classifier: Programming Language :: Python :: 3.12
Requires-Dist: python-crfsuite>=0.9.7
Requires-Dist: scikit-learn>=0.24.0
Requires-Dist: tabulate>=0.4.2
Requires-Dist: tqdm>=2.0
